README.txt
setup.py
archetypes/__init__.py
archetypes.rolefield.egg-info/PKG-INFO
archetypes.rolefield.egg-info/SOURCES.txt
archetypes.rolefield.egg-info/dependency_links.txt
archetypes.rolefield.egg-info/entry_points.txt
archetypes.rolefield.egg-info/namespace_packages.txt
archetypes.rolefield.egg-info/not-zip-safe
archetypes.rolefield.egg-info/requires.txt
archetypes.rolefield.egg-info/top_level.txt
archetypes/rolefield/__init__.py
archetypes/rolefield/configure.zcml
archetypes/rolefield/field.py
archetypes/rolefield/todo.txt
archetypes/rolefield/version.txt
archetypes/rolefield/example/__init__.py
archetypes/rolefield/example/demo.py
archetypes/rolefield/profiles/demo/types.xml
archetypes/rolefield/profiles/demo/types/RoleFieldDemoContent.xml
archetypes/rolefield/tests/__init__.py
archetypes/rolefield/tests/rolefield.txt
archetypes/rolefield/tests/test_rolefield.py
docs/HISTORY.txt
docs/INSTALL.txt
docs/LICENSE.GPL
docs/LICENSE.txt