Metadata-Version: 1.0
Name: archetypes.rolefield
Version: 0.1-a1
Summary: Archetypes Role Field
Home-page: http://plone.org/products/rolefield
Author: Ricardo Alves
Author-email: rsa@eurotux.com
License: GPL
Keywords: archetypes plone role field
Platform: UNKNOWN
Classifier: Framework :: Plone
Classifier: Programming Language :: Python
Classifier: Topic :: Software Development :: Libraries :: Python Modules
